core/__init__.py
core/ai_core.py
core/config.py
core/system_prompt.py
core/tool_utils.py
gui/__init__.py
gui/client.py
gui/completers.py
gui/config.py
gui/file_completer.py
gui/file_utils.py
gui/main.py
gui/tool_completer.py
gui/ui.py
swe_tools/__init__.py
swe_tools/cli_commander.py
swe_tools/codebase_restorer.py
swe_tools/codebase_snapshot_generator.py
swe_tools/directory_tree_viewer.py
swe_tools/file_deleter.py
swe_tools/file_fetcher.py
swe_tools/instance.py
swe_tools/internet_search.py
swe_tools/line_editor.py
swe_tools/process_manager.py
swe_tools/run_server.py
swe_tools/utils.py
clia_swe_ai-0.1.4.dist-info/METADATA
clia_swe_ai-0.1.4.dist-info/WHEEL
clia_swe_ai-0.1.4.dist-info/entry_points.txt
clia_swe_ai-0.1.4.dist-info/top_level.txt
clia_swe_ai-0.1.4.dist-info/RECORD
