Metadata-Version: 2.4
Name: clia-swe-ai
Version: 0.1.4
Summary: A CLI AI assistant for software engineering tasks.
Author-email: ayanda <past952@gmail.com>
License: MIT License
Project-URL: Homepage, https://github.com/Past-da-king/clia.git
Project-URL: Bug Tracker, https://github.com/Past-da-king/clia.git/issues
Keywords: cli,ai,software-engineering,gemini,mcp
Classifier: Programming Language :: Python :: 3
Classifier: License :: OSI Approved :: MIT License
Classifier: Operating System :: OS Independent
Classifier: Development Status :: 3 - Alpha
Classifier: Intended Audience :: Developers
Classifier: Topic :: Software Development :: Build Tools
Classifier: Topic :: Scientific/Engineering :: Artificial Intelligence
Requires-Python: >=3.8
Requires-Dist: google-genai
Requires-Dist: mcp
Requires-Dist: rich
Requires-Dist: python-dotenv
Requires-Dist: fastapi
Requires-Dist: uvicorn
Requires-Dist: psutil
